inset-1.1.5.dist-info/licenses/project/LICENSE
quark/driver/VirtualDevice.py
quark/driver/__init__.py
quark/driver/common/__init__.py
quark/driver/common/basedriver.abi3.so
quark/driver/common/basedriver.pyi
quark/driver/common/quantity.py
quark/terminal/__init__.py
quark/terminal/ssh.abi3.so
quark/terminal/terminal.abi3.so
inset-1.1.5.dist-info/METADATA
inset-1.1.5.dist-info/WHEEL
inset-1.1.5.dist-info/top_level.txt
inset-1.1.5.dist-info/RECORD
