Metadata-Version: 2.4
Name: inset
Version: 1.1.5
Summary: project description
Author-email: YL <fengyulong@pku.org.cn>
License-Expression: MIT
Project-URL: homepage, https://gitee.com
Project-URL: documentation, https://gitee.com
Project-URL: bugs, https://gitee.com
Classifier: Development Status :: 5 - Production/Stable
Classifier: Intended Audience :: Developers
Classifier: Intended Audience :: Science/Research
Classifier: Natural Language :: Chinese (Simplified)
Classifier: Natural Language :: English
Classifier: Operating System :: Microsoft :: Windows
Classifier: Operating System :: POSIX :: Linux
Classifier: Operating System :: MacOS :: MacOS X
Classifier: Programming Language :: Python :: 3.12
Classifier: Topic :: Scientific/Engineering :: Physics
Requires-Python: >=3.12
License-File: project/LICENSE
Requires-Dist: numpy
Dynamic: license-file
